pangeo_forge_cmr/__init__.py
pangeo_forge_cmr/_version.py
pangeo_forge_cmr-0.3.dist-info/LICENSE
pangeo_forge_cmr-0.3.dist-info/METADATA
pangeo_forge_cmr-0.3.dist-info/WHEEL
pangeo_forge_cmr-0.3.dist-info/top_level.txt
pangeo_forge_cmr-0.3.dist-info/RECORD
