Metadata-Version: 2.1
Name: pangeo-forge-cmr
Version: 0.3
Summary: Pipeline tools for building and publishing analysis ready datasets.
Home-page: https://github.com/yuvipanda/pangeo-forge-cmr
Maintainer: Yuvi Panda, Brianna Pagán
Maintainer-email: yuvipanda@gmail.com, briannapagan@gmail.com
License: Apache
Keywords: pangeo,data
Classifier: Development Status :: 1 - Planning
Classifier: License :: OSI Approved :: Apache Software License
Classifier: Operating System :: OS Independent
Classifier: Intended Audience :: Science/Research
Classifier: Programming Language :: Python
Classifier: Programming Language :: Python :: 3
Classifier: Programming Language :: Python :: 3.8
Classifier: Programming Language :: Python :: 3.9
Classifier: Topic :: Scientific/Engineering
Requires-Python: >=3.8
License-File: LICENSE
Requires-Dist: python-cmr
Requires-Dist: pangeo-forge-recipes
